<Ui xmlns="http://www.blizzard.com/wow/ui/">	

	<Include file="libs\oUF\oUF.xml" />
	<Script file="libs\oUF_Experience\oUF_Experience.lua" />
	<Script file="libs\oUF_Reputation\oUF_Reputation.lua" />
	<Script file="libs\oUF_AuraWatch\oUF_AuraWatch.lua" />
	
	<Script file="core\core.lua" />
	<Script file="core\functions.lua" />
	<Script file="core\events.lua" />
		
	<Script file="core\init.lua" />
	<Script file="core\commands.lua" />
	
	<Script file="settings\settings.lua" />
	<Script file="settings\media.lua" />
	<Script file="settings\colors.lua" />
	<Script file="settings\layouts.lua" />
	<Script file="settings\profiles.lua" />
	
	<Script file="modules\actionbars\Bars.lua" />
	<Script file="modules\actionbars\Bar1.lua" />
	<Script file="modules\actionbars\Bar2.lua" />
	<Script file="modules\actionbars\Bar3.lua" />
	<Script file="modules\actionbars\Bar4.lua" />
	<Script file="modules\actionbars\Bar5.lua" />
	<Script file="modules\actionbars\BarPet.lua" />
	<Script file="modules\actionbars\Bars.lua" />
	<Script file="modules\actionbars\BarShift.lua" />
	<Script file="modules\actionbars\BarTotem.lua" />
	<Script file="modules\actionbars\Bind.lua" />
	<Script file="modules\actionbars\buttons.lua" />
	<Script file="modules\actionbars\Cooldowns.lua" />
	<Script file="modules\actionbars\files.txt" />
	<Script file="modules\actionbars\Hide.lua" />
	<Script file="modules\actionbars\Others.lua" />
	<Script file="modules\actionbars\Range.lua" />
	<Script file="modules\actionbars\Style.lua" />
	
	<Script file="modules\ToolTip.lua" />
	
	<Script file="modules\ChatStyle.lua" />
	<Script file="modules\ChatLinks.lua" />
	<Script file="modules\ChatFormatting.lua" />
	
	<Script file="modules\bags.lua" />
	<Script file="modules\minimap.lua" />
	
	<Script file="modules\StatsPanel.lua" />
	<Script file="modules\Stats\Durability.lua" />
	<Script file="modules\Stats\Memory.lua" />
	<Script file="modules\Stats\Fps.lua" />
	
	<Script file="modules\SlackCheck.lua" />

	<Script file="ui\Font.lua" />
	<Script file="ui\tags.lua" />
	<Script file="ui\unitframes.lua" />
</Ui>
